[
  {
    "timestamp": "2025-11-22T08:30:52.467Z",
    "site": "example-wordpress-site",
    "url": "https://example-wordpress.com/",
    "status_code": null,
    "response_ms": 77,
    "success": false,
    "error": "getaddrinfo ENOTFOUND example-wordpress.com"
  },
  {
    "timestamp": "2025-11-22T08:30:52.467Z",
    "site": "example-shopify-store",
    "url": "https://example-store.com/",
    "status_code": null,
    "response_ms": 670,
    "success": false,
    "error": "certificate has expired"
  }
]